{"mean":{"confidence_interval":{"confidence_level":0.95,"lower_bound":84291.30254354418,"upper_bound":85911.24600680839},"point_estimate":84942.11553057528,"standard_error":431.5356021184271},"median":{"confidence_interval":{"confidence_level":0.95,"lower_bound":84292.79761904762,"upper_bound":84303.5267406205},"point_estimate":84299.30426447574,"standard_error":2.7773618897076426},"median_abs_dev":{"confidence_interval":{"confidence_level":0.95,"lower_bound":11.19994352353038,"upper_bound":48.26556167088876},"point_estimate":31.610951386777664,"standard_error":10.7574809257261},"slope":{"confidence_interval":{"confidence_level":0.95,"lower_bound":84283.18280707781,"upper_bound":84581.70516066957},"point_estimate":84396.67482463918,"standard_error":79.51758562233749},"std_dev":{"confidence_interval":{"confidence_level":0.95,"lower_bound":146.90598941607595,"upper_bound":6862.406716035689},"point_estimate":4331.590023184143,"standard_error":1787.3449016916522}}